{"summary":{"types":["Water"],"species":"Goldfish Pokémon","height":"4′3″ (1.30m)","weight":"86 lbs (39.0 kg)","abilities":["Swift Swim","Water Veil","Lightning Rod"]},"training":{"EV yield":"2 Attack ","Catch rate":"60 (7.8% with PokéBall, full HP)","Base Happiness":"70 (normal)","Base EXP":"170","Growth Rate":"Medium Fast"},"breeding":{"Egg Groups":"Water 2 ","Gender":"50% male, 50% female","Egg cycles":"20 (base 5,120 steps)"},"stats":{"HP":{"base":"80","min":"270","max":"364"},"Attack":{"base":"92","min":"170","max":"311"},"Defense":{"base":"65","min":"121","max":"251"},"Sp. Atk":{"base":"65","min":"121","max":"251"},"Sp. Def":{"base":"80","min":"148","max":"284"},"Speed":{"base":"68","min":"126","max":"258"}},"entry":{},"moves":{"byLevelUp":[],"byEgg":[],"byTutor":[],"byTM":[]},"location":{},"imageUrl":"https://img.pokemondb.net/artwork/seaking.jpg"}