{"summary":{"types":["Water","Dark"],"species":"Rogue Pokémon","height":"3′7″ (1.09m)","weight":"72.3 lbs (32.8 kg)","abilities":["Hyper Cutter","Shell Armor","Adaptability"]},"training":{"EV yield":"2 Attack ","Catch rate":"155 (20.3% with PokéBall, full HP)","Base Happiness":"70 (normal)","Base EXP":"161","Growth Rate":"Fluctuating"},"breeding":{"Egg Groups":"Water 1, Water 3 ","Gender":"50% male, 50% female","Egg cycles":"15 (base 3,840 steps)"},"stats":{"HP":{"base":"63","min":"236","max":"330"},"Attack":{"base":"120","min":"220","max":"372"},"Defense":{"base":"85","min":"157","max":"295"},"Sp. Atk":{"base":"90","min":"166","max":"306"},"Sp. Def":{"base":"55","min":"103","max":"229"},"Speed":{"base":"55","min":"103","max":"229"}},"entry":{},"moves":{"byLevelUp":[],"byEgg":[],"byTutor":[],"byTM":[]},"location":{},"imageUrl":"https://img.pokemondb.net/artwork/crawdaunt.jpg"}