{"summary":{"types":["Steel","Psychic"],"species":"Bronze Bell Pokémon","height":"4′3″ (1.30m)","weight":"412.3 lbs (187.0 kg)","abilities":["Heatproof","Levitate","Heavy Metal"]},"training":{"EV yield":"1 Defense, 1 Special Defense ","Catch rate":"90 (11.8% with PokéBall, full HP)","Base Happiness":"70 (normal)","Base EXP":"188","Growth Rate":"Medium Fast"},"breeding":{"Egg Groups":"Mineral ","Gender":"Genderless","Egg cycles":"20 (base 5,120 steps)"},"stats":{"HP":{"base":"67","min":"244","max":"338"},"Attack":{"base":"89","min":"164","max":"304"},"Defense":{"base":"116","min":"213","max":"364"},"Sp. Atk":{"base":"79","min":"146","max":"282"},"Sp. Def":{"base":"116","min":"213","max":"364"},"Speed":{"base":"33","min":"63","max":"181"}},"entry":{},"moves":{"byLevelUp":[],"byEgg":[],"byTutor":[],"byTM":[]},"location":{},"imageUrl":"https://img.pokemondb.net/artwork/bronzong.jpg"}