{"summary":{"types":["Poison"],"species":"Trash Bag Pokémon","height":"2′0″ (0.61m)","weight":"68.3 lbs (31.0 kg)","abilities":["Stench","Sticky Hold","Aftermath"]},"training":{"EV yield":"1 Speed ","Catch rate":"190 (24.8% with PokéBall, full HP)","Base Happiness":"70 (normal)","Base EXP":"66","Growth Rate":"Medium Fast"},"breeding":{"Egg Groups":"Mineral ","Gender":"50% male, 50% female","Egg cycles":"20 (base 5,120 steps)"},"stats":{"HP":{"base":"50","min":"210","max":"304"},"Attack":{"base":"50","min":"94","max":"218"},"Defense":{"base":"62","min":"116","max":"245"},"Sp. Atk":{"base":"40","min":"76","max":"196"},"Sp. Def":{"base":"62","min":"116","max":"245"},"Speed":{"base":"65","min":"121","max":"251"}},"entry":{},"moves":{"byLevelUp":[],"byEgg":[],"byTutor":[],"byTM":[]},"location":{},"imageUrl":"https://img.pokemondb.net/artwork/trubbish.jpg"}