{"summary":{"types":["Dark"],"species":"Illusion Fox Pokémon","height":"5′3″ (1.60m)","weight":"178.8 lbs (81.1 kg)","abilities":["Illusion"]},"training":{"EV yield":"2 Special Attack ","Catch rate":"45 (5.9% with PokéBall, full HP)","Base Happiness":"70 (normal)","Base EXP":"179","Growth Rate":"Medium Slow"},"breeding":{"Egg Groups":"Field ","Gender":"87.5% male, 12.5% female","Egg cycles":"20 (base 5,120 steps)"},"stats":{"HP":{"base":"60","min":"230","max":"324"},"Attack":{"base":"105","min":"193","max":"339"},"Defense":{"base":"60","min":"112","max":"240"},"Sp. Atk":{"base":"120","min":"220","max":"372"},"Sp. Def":{"base":"60","min":"112","max":"240"},"Speed":{"base":"105","min":"193","max":"339"}},"entry":{},"moves":{"byLevelUp":[],"byEgg":[],"byTutor":[],"byTM":[]},"location":{},"imageUrl":"https://img.pokemondb.net/artwork/zoroark.jpg"}