{"summary":{"types":["Ice"],"species":"Fresh Snow Pokémon","height":"1′4″ (0.41m)","weight":"12.6 lbs (5.7 kg)","abilities":["Ice Body","Snow Cloak","Weak Armor"]},"training":{"EV yield":"1 Special Attack ","Catch rate":"255 (33.3% with PokéBall, full HP)","Base Happiness":"70 (normal)","Base EXP":"61","Growth Rate":"Slow"},"breeding":{"Egg Groups":"Mineral ","Gender":"50% male, 50% female","Egg cycles":"20 (base 5,120 steps)"},"stats":{"HP":{"base":"36","min":"182","max":"276"},"Attack":{"base":"50","min":"94","max":"218"},"Defense":{"base":"50","min":"94","max":"218"},"Sp. Atk":{"base":"65","min":"121","max":"251"},"Sp. Def":{"base":"60","min":"112","max":"240"},"Speed":{"base":"44","min":"83","max":"205"}},"entry":{},"moves":{"byLevelUp":[],"byEgg":[],"byTutor":[],"byTM":[]},"location":{},"imageUrl":"https://img.pokemondb.net/artwork/vanillite.jpg"}