{"summary":{"types":["Dragon"],"species":"Axe Jaw Pokémon","height":"5′11″ (1.80m)","weight":"232.6 lbs (105.5 kg)","abilities":["Mold Breaker","Rivalry","Unnerve"]},"training":{"EV yield":"3 Attack ","Catch rate":"45 (5.9% with PokéBall, full HP)","Base Happiness":"35 (lower than normal)","Base EXP":"243","Growth Rate":"Slow"},"breeding":{"Egg Groups":"Dragon, Monster ","Gender":"50% male, 50% female","Egg cycles":"40 (base 10,240 steps)"},"stats":{"HP":{"base":"76","min":"262","max":"356"},"Attack":{"base":"147","min":"269","max":"432"},"Defense":{"base":"90","min":"166","max":"306"},"Sp. Atk":{"base":"60","min":"112","max":"240"},"Sp. Def":{"base":"70","min":"130","max":"262"},"Speed":{"base":"97","min":"179","max":"322"}},"entry":{},"moves":{"byLevelUp":[],"byEgg":[],"byTutor":[],"byTM":[]},"location":{},"imageUrl":"https://img.pokemondb.net/artwork/haxorus.jpg"}